apsg/__init__.py
apsg/config.py
apsg/shell.py
apsg/database/__init__.py
apsg/database/_alchemy.py
apsg/database/_sdbread.py
apsg/decorator/__init__.py
apsg/decorator/_decorator.py
apsg/feature/__init__.py
apsg/feature/_container.py
apsg/feature/_geodata.py
apsg/feature/_paleomag.py
apsg/feature/_statistics.py
apsg/feature/_tensor2.py
apsg/feature/_tensor3.py
apsg/helpers/__init__.py
apsg/helpers/_helper.py
apsg/helpers/_math.py
apsg/helpers/_notation.py
apsg/math/__init__.py
apsg/math/_matrix.py
apsg/math/_vector.py
apsg/pandas/__init__.py
apsg/pandas/_pandas_api.py
apsg/plotting/__init__.py
apsg/plotting/_fabricplot.py
apsg/plotting/_paleomagplots.py
apsg/plotting/_plot_artists.py
apsg/plotting/_projection.py
apsg/plotting/_roseplot.py
apsg/plotting/_stereogrid.py
apsg/plotting/_stereonet.py
apsg-1.3.7.dist-info/licenses/LICENSE
apsg-1.3.7.dist-info/METADATA
apsg-1.3.7.dist-info/WHEEL
apsg-1.3.7.dist-info/entry_points.txt
apsg-1.3.7.dist-info/top_level.txt
apsg-1.3.7.dist-info/RECORD
