Metadata-Version: 2.4
Name: apsg
Version: 1.3.7
Summary: APSG - The package for structural geologists
Author-email: Ondrej Lexa <lexa.ondrej@gmail.com>
Maintainer-email: Ondrej Lexa <lexa.ondrej@gmail.com>
License: MIT License
Project-URL: Homepage, https://github.com/ondrolexa/apsg
Project-URL: Documentation, https://apsg.readthedocs.io
Project-URL: Repository, https://github.com/ondrolexa/apsg.git
Project-URL: Issues, https://github.com/ondrolexa/apsg/issues
Project-URL: Changelog, https://github.com/ondrolexa/apsg/blob/master/CHANGELOG.md
Keywords: structural geology,stereonet,orientation data
Classifier: Development Status :: 4 - Beta
Classifier: Intended Audience :: Science/Research
Classifier: License :: OSI Approved :: MIT License
Classifier: Operating System :: OS Independent
Classifier: Programming Language :: Python :: 3
Requires-Python: >=3.10
License-File: LICENSE
Requires-Dist: numpy
Requires-Dist: matplotlib>=3.9
Requires-Dist: scipy
Requires-Dist: sqlalchemy
Requires-Dist: pandas
Provides-Extra: extra
Requires-Dist: jupyterlab; extra == "extra"
Requires-Dist: pyqt5; extra == "extra"
Provides-Extra: tests
Requires-Dist: pytest; extra == "tests"
Provides-Extra: docs
Requires-Dist: sphinx; extra == "docs"
Requires-Dist: sphinx_rtd_theme; extra == "docs"
Requires-Dist: readthedocs-sphinx-search; extra == "docs"
Requires-Dist: ipykernel; extra == "docs"
Requires-Dist: nbsphinx; extra == "docs"
Requires-Dist: autodocsumm; extra == "docs"
Provides-Extra: dev
Requires-Dist: apsg[docs,extra,tests]; extra == "dev"
Requires-Dist: black; extra == "dev"
Dynamic: license-file
